streamlit_login_auth_ui_23/__init__.py
streamlit_login_auth_ui_23/utils.py
streamlit_login_auth_ui_23/widgets.py
tests/__init__.py
tests/test___init__.py
streamlit_login_auth_ui_23-0.2.0.dist-info/LICENSE
streamlit_login_auth_ui_23-0.2.0.dist-info/METADATA
streamlit_login_auth_ui_23-0.2.0.dist-info/WHEEL
streamlit_login_auth_ui_23-0.2.0.dist-info/top_level.txt
streamlit_login_auth_ui_23-0.2.0.dist-info/RECORD
